{
  "zones": {
    "all_lights": [
      {
        "hueLightId": 2
      },
      {
        "hueLightId": 5
      },
      {
        "hueLightId": 46
      }
    ],
    "wall": [
      {
        "hueLightId": 2
      }
    ],
    "kitchen_window": [
      {
        "hueLightId": 5
      }
    ],
    "dining_table": [
      {
        "hueLightId": 46
      }
    ]
  },
  "scenes": [
    {
      "name": "Green",
      "data": [
        {
          "settings": {
            "on": true,
            "bri": 254,
            "hue": 34515,
            "sat": 236
          },
          "applyTo": [
            "wall",
            "kitchen_window"
          ]
        },
        {
          "settings": {
            "on": true,
            "bri": 254,
            "xy": [
                0.2781,
                0.4833
            ]
          },
          "applyTo": [
            "dining_table"
          ]
        }
      ]
    },
    {
      "name": "Blue",
      "data": [
        {
          "settings": {
            "on": true,
            "bri": 254,
            "xy": [
              0.1515,
              0.1135
            ]
          },
          "applyTo": [
            "wall",
            "kitchen_window",
            "dining_table"
          ]
        }
      ]
    },
    {
      "name": "All off",
      "data": [
        {
          "settings": {
            "on": false
          },
          "applyTo": [
            "all_lights"
          ]
        }
      ]
    }
  ]
}
